{
    "Messages": [
        {
            "canID": 192,
            "extendedID": true,
            "name": "CascadiaInverterCommand",
            "length": 8,
            "body": [
                {
                    "type": "uint16",
                    "name": "torque",
                    "start": 0
                },
                {
                    "type": "uint16",
                    "name": "speed",
                    "start": 2
                },
                {
                    "type": "uint8",
                    "name": "direction",
                    "start": 4
                },
                {
                    "type": "uint8",
                    "name": "flags",
                    "start": 5
                },
                {
                    "type": "uint16",
                    "name": "torqueLimit",
                    "start": 6
                }
            ]
        },
        {
            "canID": 193,
            "extendedID": true,
            "name": "CascadiaInverterParameterCommand",
            "length": 8,
            "body": [
                {
                    "type": "uint16",
                    "name": "parameterAddress",
                    "start": 0
                },
                {
                    "type": "uint8",
                    "name": "rw",
                    "start": 2
                },
                {
                    "type": "uint8",
                    "name": "reserved",
                    "start": 3
                },
                {
                    "type": "uint16",
                    "name": "data",
                    "start": 4
                },
                {
                    "type": "uint16",
                    "name": "reserved2",
                    "start": 6
                }
            ]
        },
        {
            "canID": 170,
            "extendedID": true,
            "name": "CascadiaInverterInternalStates",
            "length": 8,
            "body": [
                {
                    "type": "uint8",
                    "name": "vsmState",
                    "start": 0
                },
                {
                    "type": "uint8",
                    "name": "pwmFreq",
                    "start": 1
                },
                {
                    "type": "uint8",
                    "name": "inverterState",
                    "start": 2
                },
                {
                    "type": "uint8",
                    "name": "relayState",
                    "start": 3
                },
                {
                    "type": "bitfield",
                    "name": "modes1",
                    "start": 4,
                    "length": 1,
                    "bits": [
                        {"start": 0, "type": "bool", "name": "runMode"},
                        {"start": 5, "type": "unsigned3bit", "name": "inverterDischargeState"}
                    ]
                },
                {
                    "type": "bitfield",
                    "name": "modes2",
                    "start": 5,
                    "length": 1,
                    "bits": [
                        {"start": 0, "type": "bool", "name": "commandMode"},
                        {"start": 4, "type": "unsigned4bit", "name": "rollingValueCounter"}
                    ]
                },
                {
                    "type": "bitfield",
                    "name": "enableAndLockout",
                    "start": 6,
                    "length": 1,
                    "bits": [
                        {"start": 0, "type": "bool", "name": "enableState"},
                        {"start": 7, "type": "bool", "name": "lockoutEnable"}
                    ]
                },
                {
                    "type": "bitfield",
                    "name": "mode3",
                    "start": 7,
                    "length": 1,
                    "bits": [
                        {"start": 0, "type": "bool", "name": "directionCmd"},
                        {"start": 1, "type": "bool", "name": "bmsActive"},
                        {"start": 2, "type": "bool", "name": "bmsTorqueLimit"},
                        {"start": 3, "type": "bool", "name": "maxSpeedLimited"},
                        {"start": 4, "type": "bool", "name": "hotspotLimited"},
                        {"start": 5, "type": "bool", "name": "lowSpeedLimited"}
                    ]
                }
            ]
        },
        {
            "canID": 171,
            "extendedID": true,
            "name": "CascadiaInverterFaultCodes",
            "length": 8,
            "body": [
                {
                    "type": "bitfield",
                    "name": "postFault",
                    "start": 0,
                    "length": 4,
                    "bits": [
                        {"start": 0, "type": "bool", "name": "hwGateDesaturation"},
                        {"start": 1, "type": "bool", "name": "hwOvercurrent"},
                        {"start": 2, "type": "bool", "name": "accelShort"},
                        {"start": 3, "type": "bool", "name": "accelOpen"},
                        {"start": 4, "type": "bool", "name": "currentSenseLo"},
                        {"start": 5, "type": "bool", "name": "currentSenseHi"},
                        {"start": 6, "type": "bool", "name": "moduleTempLo"},
                        {"start": 7, "type": "bool", "name": "moduleTempHi"},
                        {"start": 8, "type": "bool", "name": "controlTempLo"},
                        {"start": 9, "type": "bool", "name": "controlTempHi"},
                        {"start": 10, "type": "bool", "name": "gateDriveTempLo"},
                        {"start": 11, "type": "bool", "name": "gateDriveTempHi"},
                        {"start": 12, "type": "bool", "name": "sense5VLo"},
                        {"start": 13, "type": "bool", "name": "sense5VHi"},
                        {"start": 14, "type": "bool", "name": "sense12VLo"},
                        {"start": 15, "type": "bool", "name": "sense12VHi"},
                        {"start": 16, "type": "bool", "name": "sense2V5VHi"},
                        {"start": 17, "type": "bool", "name": "sense2V5VLo"},
                        {"start": 18, "type": "bool", "name": "sense1V5VHi"},
                        {"start": 19, "type": "bool", "name": "sense1V5VLo"},
                        {"start": 20, "type": "bool", "name": "dcBusLo"},
                        {"start": 21, "type": "bool", "name": "dcBusHi"},
                        {"start": 22, "type": "bool", "name": "prechargeTimeout"},
                        {"start": 23, "type": "bool", "name": "prechargeFailure"},
                        {"start": 24, "type": "bool", "name": "eepromCorrupt"},
                        {"start": 25, "type": "bool", "name": "eepromBounds"},
                        {"start": 26, "type": "bool", "name": "eepromUpdate"},
                        {"start": 30, "type": "bool", "name": "brakeShort"},
                        {"start": 31, "type": "bool", "name": "brakeOpen"}
                    ]
                },
                {
                    "type": "bitfield",
                    "name": "runFault",
                    "start": 4,
                    "length": 4,
                    "bits": [
                        {"start": 0, "type": "bool", "name": "motorOverSpeed"},
                        {"start": 1, "type": "bool", "name": "overCurrent"},
                        {"start": 2, "type": "bool", "name": "overVoltage"},
                        {"start": 3, "type": "bool", "name": "inverterOverTemp"},
                        {"start": 4, "type": "bool", "name": "accelShort"},
                        {"start": 5, "type": "bool", "name": "accelOpen"},
                        {"start": 6, "type": "bool", "name": "directionCommand"},
                        {"start": 7, "type": "bool", "name": "responseTimeout"},
                        {"start": 8, "type": "bool", "name": "hwGateDesaturation"},
                        {"start": 9, "type": "bool", "name": "hwOverCurrent"},
                        {"start": 10, "type": "bool", "name": "hwUnderVoltage"},
                        {"start": 11, "type": "bool", "name": "commandMessageLost"},
                        {"start": 12, "type": "bool", "name": "motorOverTemp"},
                        {"start": 16, "type": "bool", "name": "brakeShort"},
                        {"start": 17, "type": "bool", "name": "brakeOpen"},
                        {"start": 18, "type": "bool", "name": "modAOverTem"},
                        {"start": 19, "type": "bool", "name": "modBOverTem"},
                        {"start": 20, "type": "bool", "name": "modCOverTem"},
                        {"start": 21, "type": "bool", "name": "pcbOverTemp"},
                        {"start": 22, "type": "bool", "name": "gateDrive1OverTemp"},
                        {"start": 23, "type": "bool", "name": "gateDrive2OverTemp"},
                        {"start": 24, "type": "bool", "name": "gateDrive3OverTemp"},
                        {"start": 25, "type": "bool", "name": "currentSensorFailure"},
                        {"start": 27, "type": "bool", "name": "hwOverVontage"},
                        {"start": 30, "type": "bool", "name": "resolverNotConn"},
                        {"start": 31, "type": "bool", "name": "inverterDischarging"}
                    ]
                }
            ]
        }
    ],
    "Types": {
        "uint8": {
            "length": 1,
            "ctype": "uint8_t",
            "pythonStructType": "<B"
        },
        "uint16": {
            "length": 2,
            "ctype": "uint16_t",
            "pythonStructType": "<H"
        }
    },
    "BitFieldTypes": {
        "bool": {
            "length": 1,
            "ctype": "unsigned char",
            "pythonBitStructType": "b1"
        },
        "unsigned3bit": {
            "length": 3,
            "ctype": "unsigned char",
            "pythonBitStructType": "u3"
        },
        "unsigned4bit": {
            "length": 4,
            "ctype": "unsigned char",
            "pythonBitStructType": "u4"
        }
    }
}